mobile_aat_setup/__init__.py
mobile_aat_setup/_modidx.py
mobile_aat_setup/_nbdev.py
mobile_aat_setup/change_id.py
mobile_aat_setup/core.py
mobile_aat_setup/setup.py
mobile_aat_setup-0.0.3.dist-info/LICENSE
mobile_aat_setup-0.0.3.dist-info/METADATA
mobile_aat_setup-0.0.3.dist-info/WHEEL
mobile_aat_setup-0.0.3.dist-info/entry_points.txt
mobile_aat_setup-0.0.3.dist-info/top_level.txt
mobile_aat_setup-0.0.3.dist-info/RECORD
