Metadata-Version: 2.1
Name: mobile-aat-setup
Version: 0.0.3
Summary: A project that helps setting up the mobile AAT
Home-page: https://github.com/hgzech/mobile_aat_setup
Author: hgzech
Author-email: hilmarzech@gmail.com
License: Apache Software License 2.0
Keywords: nbdev jupyter notebook python
Classifier: Development Status :: 4 - Beta
Classifier: Intended Audience :: Developers
Classifier: Natural Language :: English
Classifier: Programming Language :: Python :: 3.7
Classifier: Programming Language :: Python :: 3.8
Classifier: Programming Language :: Python :: 3.9
Classifier: Programming Language :: Python :: 3.10
Classifier: License :: OSI Approved :: Apache Software License
Requires-Python: >=3.7
License-File: LICENSE
Requires-Dist: gitpython
Provides-Extra: dev
